[
  {
    "year": "2001",
    "round": "7",
    "draft_type": "",
    "overall_pick": "197",
    "round_pick": "1",
    "team": "Twins",
    "name": "Matt Vorwald (minors)",
    "pos": "RHP",
    "war": "",
    "g_as_pitcher": "",
    "ab": "",
    "hr": "",
    "ba": "",
    "ops": "",
    "g_as_batter": "",
    "w": "",
    "l": "",
    "era": "",
    "whip": "",
    "sv": "",
    "type": "4Yr",
    "drafted_out_of": "University of Illinois at Urbana-Champaign (Champaign, IL)"
  },
  {
    "year": "2001",
    "round": "7",
    "draft_type": "",
    "overall_pick": "198",
    "round_pick": "2",
    "team": "Cubs",
    "name": "Sergio Mitre (minors)",
    "pos": "RHP",
    "war": "0.0",
    "g_as_pitcher": "145",
    "ab": "80",
    "hr": "0",
    "ba": ".138",
    "ops": ".356",
    "g_as_batter": "143",
    "w": "13",
    "l": "30",
    "era": "5.21",
    "whip": "1.49",
    "sv": "1",
    "type": "JC",
    "drafted_out_of": "San Diego City College (San Diego, CA)"
  },
  {
    "year": "2001",
    "round": "7",
    "draft_type": "",
    "overall_pick": "199",
    "round_pick": "3",
    "team": "Devil Rays",
    "name": "Tim King (minors)",
    "pos": "LHP",
    "war": "",
    "g_as_pitcher": "",
    "ab": "",
    "hr": "",
    "ba": "",
    "ops": "",
    "g_as_batter": "",
    "w": "",
    "l": "",
    "era": "",
    "whip": "",
    "sv": "",
    "type": "HS",
    "drafted_out_of": "Deer Park HS (Deer Park, TX)"
  },
  {
    "year": "2001",
    "round": "7",
    "draft_type": "",
    "overall_pick": "200",
    "round_pick": "4",
    "team": "Phillies",
    "name": "Vinnie DeChristofaro (minors)",
    "pos": "LHP",
    "war": "",
    "g_as_pitcher": "",
    "ab": "",
    "hr": "",
    "ba": "",
    "ops": "",
    "g_as_batter": "",
    "w": "",
    "l": "",
    "era": "",
    "whip": "",
    "sv": "",
    "type": "HS",
    "drafted_out_of": "Richmond Hill HS (Richmond Hill, GA)"
  },
  {
    "year": "2001",
    "round": "7",
    "draft_type": "",
    "overall_pick": "201",
    "round_pick": "5",
    "team": "Rangers",
    "name": "Patrick Boyd (minors)",
    "pos": "OF",
    "war": "",
    "g_as_pitcher": "",
    "ab": "",
    "hr": "",
    "ba": "",
    "ops": "",
    "g_as_batter": "",
    "w": "",
    "l": "",
    "era": "",
    "whip": "",
    "sv": "",
    "type": "4Yr",
    "drafted_out_of": "Clemson University (Clemson, SC)"
  },
  {
    "year": "2001",
    "round": "7",
    "draft_type": "",
    "overall_pick": "202",
    "round_pick": "6",
    "team": "Expos",
    "name": "Chad Bentz (minors)",
    "pos": "LHP",
    "war": "-0.7",
    "g_as_pitcher": "40",
    "ab": "2",
    "hr": "0",
    "ba": ".500",
    "ops": "1.000",
    "g_as_batter": "40",
    "w": "0",
    "l": "3",
    "era": "7.58",
    "whip": "1.82",
    "sv": "0",
    "type": "4Yr",
    "drafted_out_of": "California State University Long Beach (Long Beach, CA)"
  },
  {
    "year": "2001",
    "round": "7",
    "draft_type": "",
    "overall_pick": "203",
    "round_pick": "7",
    "team": "Orioles",
    "name": "Joe Coppinger (minors)",
    "pos": "RHP",
    "war": "",
    "g_as_pitcher": "",
    "ab": "",
    "hr": "",
    "ba": "",
    "ops": "",
    "g_as_batter": "",
    "w": "",
    "l": "",
    "era": "",
    "whip": "",
    "sv": "",
    "type": "JC",
    "drafted_out_of": "Seminole State College (Seminole, OK)"
  },
  {
    "year": "2001",
    "round": "7",
    "draft_type": "",
    "overall_pick": "204",
    "round_pick": "8",
    "team": "Pirates",
    "name": "Mike McCuistion (minors)",
    "pos": "C",
    "war": "",
    "g_as_pitcher": "",
    "ab": "",
    "hr": "",
    "ba": "",
    "ops": "",
    "g_as_batter": "",
    "w": "",
    "l": "",
    "era": "",
    "whip": "",
    "sv": "",
    "type": "HS",
    "drafted_out_of": "Yucaipa HS (Yucaipa, CA)"
  },
  {
    "year": "2001",
    "round": "7",
    "draft_type": "",
    "overall_pick": "205",
    "round_pick": "9",
    "team": "Royals",
    "name": "Chris Tierney (minors)",
    "pos": "LHP",
    "war": "",
    "g_as_pitcher": "",
    "ab": "",
    "hr": "",
    "ba": "",
    "ops": "",
    "g_as_batter": "",
    "w": "",
    "l": "",
    "era": "",
    "whip": "",
    "sv": "",
    "type": "HS",
    "drafted_out_of": "Rockport HS (Rockport, IL)"
  },
  {
    "year": "2001",
    "round": "7",
    "draft_type": "",
    "overall_pick": "206",
    "round_pick": "10",
    "team": "Astros",
    "name": "Ryan Stegall (minors)",
    "pos": "SS",
    "war": "",
    "g_as_pitcher": "",
    "ab": "",
    "hr": "",
    "ba": "",
    "ops": "",
    "g_as_batter": "",
    "w": "",
    "l": "",
    "era": "",
    "whip": "",
    "sv": "",
    "type": "4Yr",
    "drafted_out_of": "University of Missouri Columbia (Columbia, MO)"
  },
  {
    "year": "2001",
    "round": "7",
    "draft_type": "",
    "overall_pick": "207",
    "round_pick": "11",
    "team": "Tigers",
    "name": "Tom Farmer (minors)",
    "pos": "RHP",
    "war": "",
    "g_as_pitcher": "",
    "ab": "",
    "hr": "",
    "ba": "",
    "ops": "",
    "g_as_batter": "",
    "w": "",
    "l": "",
    "era": "",
    "whip": "",
    "sv": "",
    "type": "4Yr",
    "drafted_out_of": "University of Miami (Coral Gables, FL)"
  },
  {
    "year": "2001",
    "round": "7",
    "draft_type": "",
    "overall_pick": "208",
    "round_pick": "12",
    "team": "Brewers",
    "name": "Taylor McCormack (minors)",
    "pos": "3B",
    "war": "",
    "g_as_pitcher": "",
    "ab": "",
    "hr": "",
    "ba": "",
    "ops": "",
    "g_as_batter": "",
    "w": "",
    "l": "",
    "era": "",
    "whip": "",
    "sv": "",
    "type": "HS",
    "drafted_out_of": "Dunedin HS (Dunedin, FL)"
  },
  {
    "year": "2001",
    "round": "7",
    "draft_type": "",
    "overall_pick": "209",
    "round_pick": "13",
    "team": "Angels",
    "name": "Rich Hill (minors)",
    "pos": "LHP",
    "war": "3.3",
    "g_as_pitcher": "198",
    "ab": "114",
    "hr": "0",
    "ba": ".123",
    "ops": ".287",
    "g_as_batter": "197",
    "w": "24",
    "l": "22",
    "era": "4.72",
    "whip": "1.39",
    "sv": "0",
    "type": "4Yr",
    "drafted_out_of": "University of Michigan (Ann Arbor, MI)"
  },
  {
    "year": "2001",
    "round": "7",
    "draft_type": "",
    "overall_pick": "210",
    "round_pick": "14",
    "team": "Padres",
    "name": "Doc Brooks (minors)",
    "pos": "OF",
    "war": "",
    "g_as_pitcher": "",
    "ab": "",
    "hr": "",
    "ba": "",
    "ops": "",
    "g_as_batter": "",
    "w": "",
    "l": "",
    "era": "",
    "whip": "",
    "sv": "",
    "type": "4Yr",
    "drafted_out_of": "University of Georgia (Athens, GA)"
  },
  {
    "year": "2001",
    "round": "7",
    "draft_type": "",
    "overall_pick": "211",
    "round_pick": "15",
    "team": "Blue Jays",
    "name": "Jason Colson (minors)",
    "pos": "RHP",
    "war": "",
    "g_as_pitcher": "",
    "ab": "",
    "hr": "",
    "ba": "",
    "ops": "",
    "g_as_batter": "",
    "w": "",
    "l": "",
    "era": "",
    "whip": "",
    "sv": "",
    "type": "4Yr",
    "drafted_out_of": "Winthrop University (Rock Hill, SC)"
  },
  {
    "year": "2001",
    "round": "7",
    "draft_type": "",
    "overall_pick": "212",
    "round_pick": "16",
    "team": "Marlins",
    "name": "Lincoln Holdzkom (minors)",
    "pos": "RHP",
    "war": "",
    "g_as_pitcher": "",
    "ab": "",
    "hr": "",
    "ba": "",
    "ops": "",
    "g_as_batter": "",
    "w": "",
    "l": "",
    "era": "",
    "whip": "",
    "sv": "",
    "type": "JC",
    "drafted_out_of": "Arizona Western College (Yuma, AZ)"
  },
  {
    "year": "2001",
    "round": "7",
    "draft_type": "",
    "overall_pick": "213",
    "round_pick": "17",
    "team": "Red Sox",
    "name": "Rolando Viera (minors)",
    "pos": "LHP",
    "war": "",
    "g_as_pitcher": "",
    "ab": "",
    "hr": "",
    "ba": "",
    "ops": "",
    "g_as_batter": "",
    "w": "",
    "l": "",
    "era": "",
    "whip": "",
    "sv": "",
    "type": "",
    "drafted_out_of": ""
  },
  {
    "year": "2001",
    "round": "7",
    "draft_type": "",
    "overall_pick": "214",
    "round_pick": "18",
    "team": "Rockies",
    "name": "Cory Sullivan (minors)",
    "pos": "OF",
    "war": "0.9",
    "g_as_pitcher": "476",
    "ab": "1127",
    "hr": "10",
    "ba": ".271",
    "ops": ".708",
    "g_as_batter": "",
    "w": "",
    "l": "",
    "era": "",
    "whip": "",
    "sv": "",
    "type": "4Yr",
    "drafted_out_of": "Wake Forest University (Winston-Salem, NC)"
  },
  {
    "year": "2001",
    "round": "7",
    "draft_type": "",
    "overall_pick": "215",
    "round_pick": "19",
    "team": "Yankees",
    "name": "Andy Cannizaro (minors)",
    "pos": "SS",
    "war": "-0.0",
    "g_as_pitcher": "14",
    "ab": "9",
    "hr": "1",
    "ba": ".222",
    "ops": ".856",
    "g_as_batter": "",
    "w": "",
    "l": "",
    "era": "",
    "whip": "",
    "sv": "",
    "type": "4Yr",
    "drafted_out_of": "Tulane University (New Orleans, LA)"
  },
  {
    "year": "2001",
    "round": "7",
    "draft_type": "",
    "overall_pick": "216",
    "round_pick": "20",
    "team": "Reds",
    "name": "Bobby Basham (minors)",
    "pos": "RHP",
    "war": "",
    "g_as_pitcher": "",
    "ab": "",
    "hr": "",
    "ba": "",
    "ops": "",
    "g_as_batter": "",
    "w": "",
    "l": "",
    "era": "",
    "whip": "",
    "sv": "",
    "type": "4Yr",
    "drafted_out_of": "University of Richmond (Richmond, VA)"
  },
  {
    "year": "2001",
    "round": "7",
    "draft_type": "",
    "overall_pick": "217",
    "round_pick": "21",
    "team": "Indians",
    "name": "Josh Noviskey (minors)",
    "pos": "OF",
    "war": "",
    "g_as_pitcher": "",
    "ab": "",
    "hr": "",
    "ba": "",
    "ops": "",
    "g_as_batter": "",
    "w": "",
    "l": "",
    "era": "",
    "whip": "",
    "sv": "",
    "type": "HS",
    "drafted_out_of": "Newton HS (Newton, NJ)"
  },
  {
    "year": "2001",
    "round": "7",
    "draft_type": "",
    "overall_pick": "218",
    "round_pick": "22",
    "team": "Diamondbacks",
    "name": "Chad Tracy (minors)",
    "pos": "3B",
    "war": "5.4",
    "g_as_pitcher": "938",
    "ab": "2706",
    "hr": "86",
    "ba": ".274",
    "ops": ".772",
    "g_as_batter": "",
    "w": "",
    "l": "",
    "era": "",
    "whip": "",
    "sv": "",
    "type": "4Yr",
    "drafted_out_of": "East Carolina University (Greenville, NC)"
  },
  {
    "year": "2001",
    "round": "7",
    "draft_type": "",
    "overall_pick": "219",
    "round_pick": "23",
    "team": "Mariners",
    "name": "John Axford (minors)",
    "pos": "P",
    "war": "2.8",
    "g_as_pitcher": "343",
    "ab": "1",
    "hr": "0",
    "ba": ".000",
    "ops": ".000",
    "g_as_batter": "343",
    "w": "24",
    "l": "23",
    "era": "3.40",
    "whip": "1.35",
    "sv": "116",
    "type": "HS",
    "drafted_out_of": "Assumption College School (Port Dover, ON)"
  },
  {
    "year": "2001",
    "round": "7",
    "draft_type": "",
    "overall_pick": "220",
    "round_pick": "24",
    "team": "Dodgers",
    "name": "David Cuen (minors)",
    "pos": "LHP",
    "war": "",
    "g_as_pitcher": "",
    "ab": "",
    "hr": "",
    "ba": "",
    "ops": "",
    "g_as_batter": "",
    "w": "",
    "l": "",
    "era": "",
    "whip": "",
    "sv": "",
    "type": "HS",
    "drafted_out_of": "Cibola HS (Yuma, AZ)"
  },
  {
    "year": "2001",
    "round": "7",
    "draft_type": "",
    "overall_pick": "221",
    "round_pick": "25",
    "team": "Athletics",
    "name": "Dan Johnson (minors)",
    "pos": "1B",
    "war": "3.4",
    "g_as_pitcher": "431",
    "ab": "1363",
    "hr": "57",
    "ba": ".236",
    "ops": ".745",
    "g_as_batter": "",
    "w": "",
    "l": "",
    "era": "",
    "whip": "",
    "sv": "",
    "type": "4Yr",
    "drafted_out_of": "University of Nebraska at Lincoln (Lincoln, NE)"
  },
  {
    "year": "2001",
    "round": "7",
    "draft_type": "",
    "overall_pick": "222",
    "round_pick": "26",
    "team": "Mets",
    "name": "Tyler Beuerlein (minors)",
    "pos": "C",
    "war": "",
    "g_as_pitcher": "",
    "ab": "",
    "hr": "",
    "ba": "",
    "ops": "",
    "g_as_batter": "",
    "w": "",
    "l": "",
    "era": "",
    "whip": "",
    "sv": "",
    "type": "4Yr",
    "drafted_out_of": "Grand Canyon University (Phoenix, AZ)"
  },
  {
    "year": "2001",
    "round": "7",
    "draft_type": "",
    "overall_pick": "223",
    "round_pick": "27",
    "team": "White Sox",
    "name": "Brandon Camardese (minors)",
    "pos": "LHP",
    "war": "",
    "g_as_pitcher": "",
    "ab": "",
    "hr": "",
    "ba": "",
    "ops": "",
    "g_as_batter": "",
    "w": "",
    "l": "",
    "era": "",
    "whip": "",
    "sv": "",
    "type": "HS",
    "drafted_out_of": "Chaminade HS (Hollywood, FL)"
  },
  {
    "year": "2001",
    "round": "7",
    "draft_type": "",
    "overall_pick": "224",
    "round_pick": "28",
    "team": "Cardinals",
    "name": "Tyler Adamczyk (minors)",
    "pos": "RHP",
    "war": "",
    "g_as_pitcher": "",
    "ab": "",
    "hr": "",
    "ba": "",
    "ops": "",
    "g_as_batter": "",
    "w": "",
    "l": "",
    "era": "",
    "whip": "",
    "sv": "",
    "type": "HS",
    "drafted_out_of": "Westlake HS (Westlake Village, CA)"
  },
  {
    "year": "2001",
    "round": "7",
    "draft_type": "",
    "overall_pick": "225",
    "round_pick": "29",
    "team": "Braves",
    "name": "Raymond Nieves (minors)",
    "pos": "RHP",
    "war": "",
    "g_as_pitcher": "",
    "ab": "",
    "hr": "",
    "ba": "",
    "ops": "",
    "g_as_batter": "",
    "w": "",
    "l": "",
    "era": "",
    "whip": "",
    "sv": "",
    "type": "HS",
    "drafted_out_of": "De Gracis HS (Vega Alta, PR)"
  },
  {
    "year": "2001",
    "round": "7",
    "draft_type": "",
    "overall_pick": "226",
    "round_pick": "30",
    "team": "Giants",
    "name": "Jamie Athas (minors)",
    "pos": "SS",
    "war": "",
    "g_as_pitcher": "",
    "ab": "",
    "hr": "",
    "ba": "",
    "ops": "",
    "g_as_batter": "",
    "w": "",
    "l": "",
    "era": "",
    "whip": "",
    "sv": "",
    "type": "4Yr",
    "drafted_out_of": "Wake Forest University (Winston-Salem, NC)"
  }
]
