[
  {
    "year": "2004",
    "round": "8",
    "draft_type": "",
    "overall_pick": "222",
    "round_pick": "1",
    "team": "Padres",
    "name": "Vern Sterry (minors)",
    "pos": "RHP",
    "war": "",
    "g_as_pitcher": "",
    "ab": "",
    "hr": "",
    "ba": "",
    "ops": "",
    "g_as_batter": "",
    "w": "",
    "l": "",
    "era": "",
    "whip": "",
    "sv": "",
    "type": "4Yr",
    "drafted_out_of": "North Carolina State University (Raleigh, NC)"
  },
  {
    "year": "2004",
    "round": "8",
    "draft_type": "",
    "overall_pick": "223",
    "round_pick": "2",
    "team": "Tigers",
    "name": "Luke French (minors)",
    "pos": "LHP",
    "war": "0.1",
    "g_as_pitcher": "31",
    "ab": "1",
    "hr": "0",
    "ba": ".000",
    "ops": ".000",
    "g_as_batter": "31",
    "w": "9",
    "l": "12",
    "era": "4.99",
    "whip": "1.50",
    "sv": "0",
    "type": "HS",
    "drafted_out_of": "Heritage HS (Littleton, CO)"
  },
  {
    "year": "2004",
    "round": "8",
    "draft_type": "",
    "overall_pick": "224",
    "round_pick": "3",
    "team": "Mets",
    "name": "Neil Jamison (minors)",
    "pos": "RHP",
    "war": "",
    "g_as_pitcher": "",
    "ab": "",
    "hr": "",
    "ba": "",
    "ops": "",
    "g_as_batter": "",
    "w": "",
    "l": "",
    "era": "",
    "whip": "",
    "sv": "",
    "type": "4Yr",
    "drafted_out_of": "California State University San Bernardino (San Bernardino, CA)"
  },
  {
    "year": "2004",
    "round": "8",
    "draft_type": "",
    "overall_pick": "225",
    "round_pick": "4",
    "team": "Devil Rays",
    "name": "Rhyne Hughes (minors)",
    "pos": "1B",
    "war": "-0.1",
    "g_as_pitcher": "14",
    "ab": "47",
    "hr": "0",
    "ba": ".213",
    "ops": ".530",
    "g_as_batter": "",
    "w": "",
    "l": "",
    "era": "",
    "whip": "",
    "sv": "",
    "type": "JC",
    "drafted_out_of": "Pearl River Community College (Poplarville, MS)"
  },
  {
    "year": "2004",
    "round": "8",
    "draft_type": "",
    "overall_pick": "226",
    "round_pick": "5",
    "team": "Brewers",
    "name": "Brandon Parillo (minors)",
    "pos": "LHP",
    "war": "",
    "g_as_pitcher": "",
    "ab": "",
    "hr": "",
    "ba": "",
    "ops": "",
    "g_as_batter": "",
    "w": "",
    "l": "",
    "era": "",
    "whip": "",
    "sv": "",
    "type": "HS",
    "drafted_out_of": "Marina HS (Huntington Beach, CA)"
  },
  {
    "year": "2004",
    "round": "8",
    "draft_type": "",
    "overall_pick": "227",
    "round_pick": "6",
    "team": "Indians",
    "name": "Justin Pekarek (minors)",
    "pos": "LHP",
    "war": "",
    "g_as_pitcher": "",
    "ab": "",
    "hr": "",
    "ba": "",
    "ops": "",
    "g_as_batter": "",
    "w": "",
    "l": "",
    "era": "",
    "whip": "",
    "sv": "",
    "type": "4Yr",
    "drafted_out_of": "University of Nebraska at Lincoln (Lincoln, NE)"
  },
  {
    "year": "2004",
    "round": "8",
    "draft_type": "",
    "overall_pick": "228",
    "round_pick": "7",
    "team": "Reds",
    "name": "Greg Goetz (minors)",
    "pos": "LHP",
    "war": "",
    "g_as_pitcher": "",
    "ab": "",
    "hr": "",
    "ba": "",
    "ops": "",
    "g_as_batter": "",
    "w": "",
    "l": "",
    "era": "",
    "whip": "",
    "sv": "",
    "type": "JC",
    "drafted_out_of": "Bellevue Community College (Bellevue, WA)"
  },
  {
    "year": "2004",
    "round": "8",
    "draft_type": "",
    "overall_pick": "229",
    "round_pick": "8",
    "team": "Orioles",
    "name": "Dave Haehnel (minors)",
    "pos": "LHP",
    "war": "",
    "g_as_pitcher": "",
    "ab": "",
    "hr": "",
    "ba": "",
    "ops": "",
    "g_as_batter": "",
    "w": "",
    "l": "",
    "era": "",
    "whip": "",
    "sv": "",
    "type": "4Yr",
    "drafted_out_of": "University of Illinois at Urbana-Champaign (Champaign, IL)"
  },
  {
    "year": "2004",
    "round": "8",
    "draft_type": "",
    "overall_pick": "230",
    "round_pick": "9",
    "team": "Rockies",
    "name": "Jim Miller (minors)",
    "pos": "RHP",
    "war": "0.9",
    "g_as_pitcher": "50",
    "ab": "0",
    "hr": "0",
    "ba": "",
    "ops": "",
    "g_as_batter": "50",
    "w": "2",
    "l": "3",
    "era": "3.48",
    "whip": "1.49",
    "sv": "1",
    "type": "4Yr",
    "drafted_out_of": "University of Louisiana at Monroe (Monroe, LA)"
  },
  {
    "year": "2004",
    "round": "8",
    "draft_type": "",
    "overall_pick": "231",
    "round_pick": "10",
    "team": "Rangers",
    "name": "Mark Roberts (minors)",
    "pos": "RHP",
    "war": "",
    "g_as_pitcher": "",
    "ab": "",
    "hr": "",
    "ba": "",
    "ops": "",
    "g_as_batter": "",
    "w": "",
    "l": "",
    "era": "",
    "whip": "",
    "sv": "",
    "type": "4Yr",
    "drafted_out_of": "University of Oklahoma (Norman, OK)"
  },
  {
    "year": "2004",
    "round": "8",
    "draft_type": "",
    "overall_pick": "232",
    "round_pick": "11",
    "team": "Pirates",
    "name": "Eric Ridener (minors)",
    "pos": "RHP",
    "war": "",
    "g_as_pitcher": "",
    "ab": "",
    "hr": "",
    "ba": "",
    "ops": "",
    "g_as_batter": "",
    "w": "",
    "l": "",
    "era": "",
    "whip": "",
    "sv": "",
    "type": "HS",
    "drafted_out_of": "Taravella HS (Coral Springs, FL)"
  },
  {
    "year": "2004",
    "round": "8",
    "draft_type": "",
    "overall_pick": "233",
    "round_pick": "12",
    "team": "Angels",
    "name": "Freddy Sandoval (minors)",
    "pos": "SS",
    "war": "-0.2",
    "g_as_pitcher": "11",
    "ab": "17",
    "hr": "0",
    "ba": ".176",
    "ops": ".458",
    "g_as_batter": "",
    "w": "",
    "l": "",
    "era": "",
    "whip": "",
    "sv": "",
    "type": "4Yr",
    "drafted_out_of": "University of San Diego (San Diego, CA)"
  },
  {
    "year": "2004",
    "round": "8",
    "draft_type": "",
    "overall_pick": "234",
    "round_pick": "13",
    "team": "Expos",
    "name": "Leonard Davis (minors)",
    "pos": "3B",
    "war": "",
    "g_as_pitcher": "",
    "ab": "",
    "hr": "",
    "ba": "",
    "ops": "",
    "g_as_batter": "",
    "w": "",
    "l": "",
    "era": "",
    "whip": "",
    "sv": "",
    "type": "JC",
    "drafted_out_of": "Fresno City College (Fresno, CA)"
  },
  {
    "year": "2004",
    "round": "8",
    "draft_type": "",
    "overall_pick": "235",
    "round_pick": "14",
    "team": "Royals",
    "name": "Ed Lucas (minors)",
    "pos": "SS",
    "war": "1.2",
    "g_as_pitcher": "163",
    "ab": "530",
    "hr": "5",
    "ba": ".255",
    "ops": ".624",
    "g_as_batter": "",
    "w": "",
    "l": "",
    "era": "",
    "whip": "",
    "sv": "",
    "type": "4Yr",
    "drafted_out_of": "Dartmouth College (Hanover, NH)"
  },
  {
    "year": "2004",
    "round": "8",
    "draft_type": "",
    "overall_pick": "236",
    "round_pick": "15",
    "team": "Diamondbacks",
    "name": "James Shull (minors)",
    "pos": "RHP",
    "war": "",
    "g_as_pitcher": "",
    "ab": "",
    "hr": "",
    "ba": "",
    "ops": "",
    "g_as_batter": "",
    "w": "",
    "l": "",
    "era": "",
    "whip": "",
    "sv": "",
    "type": "4Yr",
    "drafted_out_of": "California Polytechnic State University, San Luis Obispo (San Luis Obispo, CA)"
  },
  {
    "year": "2004",
    "round": "8",
    "draft_type": "",
    "overall_pick": "237",
    "round_pick": "16",
    "team": "Blue Jays",
    "name": "Chip Cannon (minors)",
    "pos": "1B",
    "war": "",
    "g_as_pitcher": "",
    "ab": "",
    "hr": "",
    "ba": "",
    "ops": "",
    "g_as_batter": "",
    "w": "",
    "l": "",
    "era": "",
    "whip": "",
    "sv": "",
    "type": "4Yr",
    "drafted_out_of": "The Citadel (Charleston, SC)"
  },
  {
    "year": "2004",
    "round": "8",
    "draft_type": "",
    "overall_pick": "238",
    "round_pick": "17",
    "team": "Dodgers",
    "name": "Carlos Medero-Stullz (minors)",
    "pos": "C",
    "war": "",
    "g_as_pitcher": "",
    "ab": "",
    "hr": "",
    "ba": "",
    "ops": "",
    "g_as_batter": "",
    "w": "",
    "l": "",
    "era": "",
    "whip": "",
    "sv": "",
    "type": "HS",
    "drafted_out_of": "Goleman HS (Miami, FL)"
  },
  {
    "year": "2004",
    "round": "8",
    "draft_type": "",
    "overall_pick": "239",
    "round_pick": "18",
    "team": "White Sox",
    "name": "Nik Lemon (minors)",
    "pos": "RHP",
    "war": "",
    "g_as_pitcher": "",
    "ab": "",
    "hr": "",
    "ba": "",
    "ops": "",
    "g_as_batter": "",
    "w": "",
    "l": "",
    "era": "",
    "whip": "",
    "sv": "",
    "type": "4Yr",
    "drafted_out_of": "Brigham Young University (Provo, UT)"
  },
  {
    "year": "2004",
    "round": "8",
    "draft_type": "",
    "overall_pick": "240",
    "round_pick": "19",
    "team": "Cardinals",
    "name": "Matt Shepherd (minors)",
    "pos": "SS",
    "war": "",
    "g_as_pitcher": "",
    "ab": "",
    "hr": "",
    "ba": "",
    "ops": "",
    "g_as_batter": "",
    "w": "",
    "l": "",
    "era": "",
    "whip": "",
    "sv": "",
    "type": "4Yr",
    "drafted_out_of": "University of Southern Mississippi (Hattiesburg, MS)"
  },
  {
    "year": "2004",
    "round": "8",
    "draft_type": "",
    "overall_pick": "241",
    "round_pick": "20",
    "team": "Twins",
    "name": "Jay Sawatski (minors)",
    "pos": "LHP",
    "war": "",
    "g_as_pitcher": "",
    "ab": "",
    "hr": "",
    "ba": "",
    "ops": "",
    "g_as_batter": "",
    "w": "",
    "l": "",
    "era": "",
    "whip": "",
    "sv": "",
    "type": "4Yr",
    "drafted_out_of": "University of Arkansas (Fayetteville, AR)"
  },
  {
    "year": "2004",
    "round": "8",
    "draft_type": "",
    "overall_pick": "242",
    "round_pick": "21",
    "team": "Phillies",
    "name": "Sam Orr (minors)",
    "pos": "SS",
    "war": "",
    "g_as_pitcher": "",
    "ab": "",
    "hr": "",
    "ba": "",
    "ops": "",
    "g_as_batter": "",
    "w": "",
    "l": "",
    "era": "",
    "whip": "",
    "sv": "",
    "type": "4Yr",
    "drafted_out_of": "Biola University (La Mirada, CA)"
  },
  {
    "year": "2004",
    "round": "8",
    "draft_type": "",
    "overall_pick": "243",
    "round_pick": "22",
    "team": "Mariners",
    "name": "Marshall Hubbard (minors)",
    "pos": "1B",
    "war": "",
    "g_as_pitcher": "",
    "ab": "",
    "hr": "",
    "ba": "",
    "ops": "",
    "g_as_batter": "",
    "w": "",
    "l": "",
    "era": "",
    "whip": "",
    "sv": "",
    "type": "4Yr",
    "drafted_out_of": "University of North Carolina at Asheville (Asheville, NC)"
  },
  {
    "year": "2004",
    "round": "8",
    "draft_type": "",
    "overall_pick": "244",
    "round_pick": "23",
    "team": "Astros",
    "name": "Evan Englebrook (minors)",
    "pos": "RHP",
    "war": "",
    "g_as_pitcher": "",
    "ab": "",
    "hr": "",
    "ba": "",
    "ops": "",
    "g_as_batter": "",
    "w": "",
    "l": "",
    "era": "",
    "whip": "",
    "sv": "",
    "type": "4Yr",
    "drafted_out_of": "Shippensburg University of Pennsylvania (Shippensburg, PA)"
  },
  {
    "year": "2004",
    "round": "8",
    "draft_type": "",
    "overall_pick": "245",
    "round_pick": "24",
    "team": "Red Sox",
    "name": "Kyle Bono (minors)",
    "pos": "RHP",
    "war": "",
    "g_as_pitcher": "",
    "ab": "",
    "hr": "",
    "ba": "",
    "ops": "",
    "g_as_batter": "",
    "w": "",
    "l": "",
    "era": "",
    "whip": "",
    "sv": "",
    "type": "4Yr",
    "drafted_out_of": "University of Central Florida (Orlando, FL)"
  },
  {
    "year": "2004",
    "round": "8",
    "draft_type": "",
    "overall_pick": "246",
    "round_pick": "25",
    "team": "Cubs",
    "name": "Eric Patterson (minors)",
    "pos": "2B",
    "war": "-0.1",
    "g_as_pitcher": "226",
    "ab": "508",
    "hr": "10",
    "ba": ".217",
    "ops": ".637",
    "g_as_batter": "",
    "w": "",
    "l": "",
    "era": "",
    "whip": "",
    "sv": "",
    "type": "4Yr",
    "drafted_out_of": "Georgia Institute of Technology (Atlanta, GA)"
  },
  {
    "year": "2004",
    "round": "8",
    "draft_type": "",
    "overall_pick": "247",
    "round_pick": "26",
    "team": "Athletics",
    "name": "Myron Leslie (minors)",
    "pos": "3B",
    "war": "",
    "g_as_pitcher": "",
    "ab": "",
    "hr": "",
    "ba": "",
    "ops": "",
    "g_as_batter": "",
    "w": "",
    "l": "",
    "era": "",
    "whip": "",
    "sv": "",
    "type": "4Yr",
    "drafted_out_of": "University of South Florida (Tampa, FL)"
  },
  {
    "year": "2004",
    "round": "8",
    "draft_type": "",
    "overall_pick": "248",
    "round_pick": "27",
    "team": "Marlins",
    "name": "Craig Molldrem (minors)",
    "pos": "RHP",
    "war": "",
    "g_as_pitcher": "",
    "ab": "",
    "hr": "",
    "ba": "",
    "ops": "",
    "g_as_batter": "",
    "w": "",
    "l": "",
    "era": "",
    "whip": "",
    "sv": "",
    "type": "4Yr",
    "drafted_out_of": "University of Minnesota, Duluth (Duluth, MN)"
  },
  {
    "year": "2004",
    "round": "8",
    "draft_type": "",
    "overall_pick": "249",
    "round_pick": "28",
    "team": "Yankees",
    "name": "Mike Martinez (minors)",
    "pos": "RHP",
    "war": "",
    "g_as_pitcher": "",
    "ab": "",
    "hr": "",
    "ba": "",
    "ops": "",
    "g_as_batter": "",
    "w": "",
    "l": "",
    "era": "",
    "whip": "",
    "sv": "",
    "type": "4Yr",
    "drafted_out_of": "California State University Fullerton (Fullerton, CA)"
  },
  {
    "year": "2004",
    "round": "8",
    "draft_type": "",
    "overall_pick": "250",
    "round_pick": "29",
    "team": "Giants",
    "name": "Omar Aguilar (minors)",
    "pos": "RHP",
    "war": "",
    "g_as_pitcher": "",
    "ab": "",
    "hr": "",
    "ba": "",
    "ops": "",
    "g_as_batter": "",
    "w": "",
    "l": "",
    "era": "",
    "whip": "",
    "sv": "",
    "type": "JC",
    "drafted_out_of": "Merced College (Merced, CA)"
  },
  {
    "year": "2004",
    "round": "8",
    "draft_type": "",
    "overall_pick": "251",
    "round_pick": "30",
    "team": "Braves",
    "name": "Derrick Arnold (minors)",
    "pos": "SS",
    "war": "",
    "g_as_pitcher": "",
    "ab": "",
    "hr": "",
    "ba": "",
    "ops": "",
    "g_as_batter": "",
    "w": "",
    "l": "",
    "era": "",
    "whip": "",
    "sv": "",
    "type": "JC",
    "drafted_out_of": "Tallahassee Community College (Tallahassee, FL)"
  }
]
