[
  {
    "year": "2011",
    "round": "7",
    "draft_type": "",
    "overall_pick": "212",
    "round_pick": "1",
    "team": "Pirates",
    "name": "Jake Burnette (minors)",
    "pos": "RHP",
    "war": "",
    "g_as_pitcher": "",
    "ab": "",
    "hr": "",
    "ba": "",
    "ops": "",
    "g_as_batter": "",
    "w": "",
    "l": "",
    "era": "",
    "whip": "",
    "sv": "",
    "type": "HS",
    "drafted_out_of": "Buford HS (Buford, GA)"
  },
  {
    "year": "2011",
    "round": "7",
    "draft_type": "",
    "overall_pick": "213",
    "round_pick": "2",
    "team": "Mariners",
    "name": "Steven Proscia (minors)",
    "pos": "3B",
    "war": "",
    "g_as_pitcher": "",
    "ab": "",
    "hr": "",
    "ba": "",
    "ops": "",
    "g_as_batter": "",
    "w": "",
    "l": "",
    "era": "",
    "whip": "",
    "sv": "",
    "type": "4Yr",
    "drafted_out_of": "University of Virginia (Charlottesville, VA)"
  },
  {
    "year": "2011",
    "round": "7",
    "draft_type": "",
    "overall_pick": "214",
    "round_pick": "3",
    "team": "Diamondbacks",
    "name": "Ben Roberts (minors)",
    "pos": "CF",
    "war": "",
    "g_as_pitcher": "",
    "ab": "",
    "hr": "",
    "ba": "",
    "ops": "",
    "g_as_batter": "",
    "w": "",
    "l": "",
    "era": "",
    "whip": "",
    "sv": "",
    "type": "HS",
    "drafted_out_of": "Sentinel MS (Missoula, MT)"
  },
  {
    "year": "2011",
    "round": "7",
    "draft_type": "",
    "overall_pick": "215",
    "round_pick": "4",
    "team": "Orioles",
    "name": "Trent Howard (minors)",
    "pos": "LHP",
    "war": "",
    "g_as_pitcher": "",
    "ab": "",
    "hr": "",
    "ba": "",
    "ops": "",
    "g_as_batter": "",
    "w": "",
    "l": "",
    "era": "",
    "whip": "",
    "sv": "",
    "type": "4Yr",
    "drafted_out_of": "Central Michigan University (Mount Pleasant, MI)"
  },
  {
    "year": "2011",
    "round": "7",
    "draft_type": "",
    "overall_pick": "216",
    "round_pick": "5",
    "team": "Royals",
    "name": "Kellen Moen (minors)",
    "pos": "RHP",
    "war": "",
    "g_as_pitcher": "",
    "ab": "",
    "hr": "",
    "ba": "",
    "ops": "",
    "g_as_batter": "",
    "w": "",
    "l": "",
    "era": "",
    "whip": "",
    "sv": "",
    "type": "4Yr",
    "drafted_out_of": "University of Oregon (Eugene, OR)"
  },
  {
    "year": "2011",
    "round": "7",
    "draft_type": "",
    "overall_pick": "217",
    "round_pick": "6",
    "team": "Nationals",
    "name": "Brian Dupra (minors)",
    "pos": "RHP",
    "war": "",
    "g_as_pitcher": "",
    "ab": "",
    "hr": "",
    "ba": "",
    "ops": "",
    "g_as_batter": "",
    "w": "",
    "l": "",
    "era": "",
    "whip": "",
    "sv": "",
    "type": "4Yr",
    "drafted_out_of": "University of Notre Dame (South Bend, IN)"
  },
  {
    "year": "2011",
    "round": "7",
    "draft_type": "",
    "overall_pick": "218",
    "round_pick": "7",
    "team": "Indians",
    "name": "Eric Haase (minors)",
    "pos": "C",
    "war": "",
    "g_as_pitcher": "",
    "ab": "",
    "hr": "",
    "ba": "",
    "ops": "",
    "g_as_batter": "",
    "w": "",
    "l": "",
    "era": "",
    "whip": "",
    "sv": "",
    "type": "HS",
    "drafted_out_of": "Divine Child HS (Dearborn, MI)"
  },
  {
    "year": "2011",
    "round": "7",
    "draft_type": "",
    "overall_pick": "219",
    "round_pick": "8",
    "team": "Cubs",
    "name": "Trevor Gretzky (minors)",
    "pos": "1B",
    "war": "",
    "g_as_pitcher": "",
    "ab": "",
    "hr": "",
    "ba": "",
    "ops": "",
    "g_as_batter": "",
    "w": "",
    "l": "",
    "era": "",
    "whip": "",
    "sv": "",
    "type": "HS",
    "drafted_out_of": "Oaks Christian HS (Westlake, CA)"
  },
  {
    "year": "2011",
    "round": "7",
    "draft_type": "",
    "overall_pick": "220",
    "round_pick": "9",
    "team": "Astros",
    "name": "Javaris Reynolds (minors)",
    "pos": "CF",
    "war": "",
    "g_as_pitcher": "",
    "ab": "",
    "hr": "",
    "ba": "",
    "ops": "",
    "g_as_batter": "",
    "w": "",
    "l": "",
    "era": "",
    "whip": "",
    "sv": "",
    "type": "HS",
    "drafted_out_of": "King HS (Tampa, FL)"
  },
  {
    "year": "2011",
    "round": "7",
    "draft_type": "",
    "overall_pick": "221",
    "round_pick": "10",
    "team": "Brewers",
    "name": "David Goforth (minors)",
    "pos": "RHP",
    "war": "",
    "g_as_pitcher": "",
    "ab": "",
    "hr": "",
    "ba": "",
    "ops": "",
    "g_as_batter": "",
    "w": "",
    "l": "",
    "era": "",
    "whip": "",
    "sv": "",
    "type": "4Yr",
    "drafted_out_of": "University of Mississippi (Oxford, MS)"
  },
  {
    "year": "2011",
    "round": "7",
    "draft_type": "",
    "overall_pick": "222",
    "round_pick": "11",
    "team": "Mets",
    "name": "Cole Frenzel (minors)",
    "pos": "1B",
    "war": "",
    "g_as_pitcher": "",
    "ab": "",
    "hr": "",
    "ba": "",
    "ops": "",
    "g_as_batter": "",
    "w": "",
    "l": "",
    "era": "",
    "whip": "",
    "sv": "",
    "type": "4Yr",
    "drafted_out_of": "University of Arizona (Tucson, AZ)"
  },
  {
    "year": "2011",
    "round": "7",
    "draft_type": "",
    "overall_pick": "223",
    "round_pick": "12",
    "team": "Marlins",
    "name": "Ryan Rieger (minors)",
    "pos": "1B",
    "war": "",
    "g_as_pitcher": "",
    "ab": "",
    "hr": "",
    "ba": "",
    "ops": "",
    "g_as_batter": "",
    "w": "",
    "l": "",
    "era": "",
    "whip": "",
    "sv": "",
    "type": "JC",
    "drafted_out_of": "College of the Sequoias (Visalia, CA)"
  },
  {
    "year": "2011",
    "round": "7",
    "draft_type": "",
    "overall_pick": "224",
    "round_pick": "13",
    "team": "Dodgers",
    "name": "Scott Woodward (minors)",
    "pos": "3B",
    "war": "",
    "g_as_pitcher": "",
    "ab": "",
    "hr": "",
    "ba": "",
    "ops": "",
    "g_as_batter": "",
    "w": "",
    "l": "",
    "era": "",
    "whip": "",
    "sv": "",
    "type": "4Yr",
    "drafted_out_of": "Coastal Carolina University (Conway, SC)"
  },
  {
    "year": "2011",
    "round": "7",
    "draft_type": "",
    "overall_pick": "225",
    "round_pick": "14",
    "team": "Angels",
    "name": "Abel Baker (minors)",
    "pos": "C",
    "war": "",
    "g_as_pitcher": "",
    "ab": "",
    "hr": "",
    "ba": "",
    "ops": "",
    "g_as_batter": "",
    "w": "",
    "l": "",
    "era": "",
    "whip": "",
    "sv": "",
    "type": "JC",
    "drafted_out_of": "Grayson County College (Denison, TX)"
  },
  {
    "year": "2011",
    "round": "7",
    "draft_type": "",
    "overall_pick": "226",
    "round_pick": "15",
    "team": "Athletics",
    "name": "Blake Treinen (minors)",
    "pos": "RHP",
    "war": "1.1",
    "g_as_pitcher": "15",
    "ab": "12",
    "hr": "0",
    "ba": ".083",
    "ops": ".237",
    "g_as_batter": "15",
    "w": "2",
    "l": "3",
    "era": "2.49",
    "whip": "1.38",
    "sv": "0",
    "type": "4Yr",
    "drafted_out_of": "South Dakota State University (Brookings, SD)"
  },
  {
    "year": "2011",
    "round": "7",
    "draft_type": "",
    "overall_pick": "227",
    "round_pick": "16",
    "team": "Tigers",
    "name": "Brian Flynn (minors)",
    "pos": "LHP",
    "war": "-0.8",
    "g_as_pitcher": "6",
    "ab": "7",
    "hr": "0",
    "ba": ".286",
    "ops": ".571",
    "g_as_batter": "6",
    "w": "0",
    "l": "3",
    "era": "8.64",
    "whip": "2.20",
    "sv": "0",
    "type": "4Yr",
    "drafted_out_of": "Wichita State University (Wichita, KS)"
  },
  {
    "year": "2011",
    "round": "7",
    "draft_type": "",
    "overall_pick": "228",
    "round_pick": "17",
    "team": "Rockies",
    "name": "Harold Riggins (minors)",
    "pos": "1B",
    "war": "",
    "g_as_pitcher": "",
    "ab": "",
    "hr": "",
    "ba": "",
    "ops": "",
    "g_as_batter": "",
    "w": "",
    "l": "",
    "era": "",
    "whip": "",
    "sv": "",
    "type": "4Yr",
    "drafted_out_of": "North Carolina State University (Raleigh, NC)"
  },
  {
    "year": "2011",
    "round": "7",
    "draft_type": "",
    "overall_pick": "229",
    "round_pick": "18",
    "team": "Blue Jays",
    "name": "Christian Lopes (minors)",
    "pos": "SS",
    "war": "",
    "g_as_pitcher": "",
    "ab": "",
    "hr": "",
    "ba": "",
    "ops": "",
    "g_as_batter": "",
    "w": "",
    "l": "",
    "era": "",
    "whip": "",
    "sv": "",
    "type": "HS",
    "drafted_out_of": "Edison HS (Huntington Beach, CA)"
  },
  {
    "year": "2011",
    "round": "7",
    "draft_type": "",
    "overall_pick": "230",
    "round_pick": "19",
    "team": "Cardinals",
    "name": "Nick Martini (minors)",
    "pos": "CF",
    "war": "",
    "g_as_pitcher": "",
    "ab": "",
    "hr": "",
    "ba": "",
    "ops": "",
    "g_as_batter": "",
    "w": "",
    "l": "",
    "era": "",
    "whip": "",
    "sv": "",
    "type": "4Yr",
    "drafted_out_of": "Kansas State University (Manhattan, KS)"
  },
  {
    "year": "2011",
    "round": "7",
    "draft_type": "",
    "overall_pick": "231",
    "round_pick": "20",
    "team": "White Sox",
    "name": "Kevan Smith (minors)",
    "pos": "C",
    "war": "",
    "g_as_pitcher": "",
    "ab": "",
    "hr": "",
    "ba": "",
    "ops": "",
    "g_as_batter": "",
    "w": "",
    "l": "",
    "era": "",
    "whip": "",
    "sv": "",
    "type": "4Yr",
    "drafted_out_of": "University of Pittsburgh (Pittsburgh, PA)"
  },
  {
    "year": "2011",
    "round": "7",
    "draft_type": "",
    "overall_pick": "232",
    "round_pick": "21",
    "team": "Red Sox",
    "name": "Cody Kukuk (minors)",
    "pos": "LHP",
    "war": "",
    "g_as_pitcher": "",
    "ab": "",
    "hr": "",
    "ba": "",
    "ops": "",
    "g_as_batter": "",
    "w": "",
    "l": "",
    "era": "",
    "whip": "",
    "sv": "",
    "type": "HS",
    "drafted_out_of": "Free State HS (Lawrence, KS)"
  },
  {
    "year": "2011",
    "round": "7",
    "draft_type": "",
    "overall_pick": "233",
    "round_pick": "22",
    "team": "Padres",
    "name": "Matt Wisler (minors)",
    "pos": "RHP",
    "war": "",
    "g_as_pitcher": "",
    "ab": "",
    "hr": "",
    "ba": "",
    "ops": "",
    "g_as_batter": "",
    "w": "",
    "l": "",
    "era": "",
    "whip": "",
    "sv": "",
    "type": "HS",
    "drafted_out_of": "Bryan HS (Bryan, OH)"
  },
  {
    "year": "2011",
    "round": "7",
    "draft_type": "",
    "overall_pick": "234",
    "round_pick": "23",
    "team": "Rangers",
    "name": "Max Pentecost (minors)",
    "pos": "C",
    "war": "",
    "g_as_pitcher": "",
    "ab": "",
    "hr": "",
    "ba": "",
    "ops": "",
    "g_as_batter": "",
    "w": "",
    "l": "",
    "era": "",
    "whip": "",
    "sv": "",
    "type": "HS",
    "drafted_out_of": "Winder-Barrow HS (Winder, GA)"
  },
  {
    "year": "2011",
    "round": "7",
    "draft_type": "",
    "overall_pick": "235",
    "round_pick": "24",
    "team": "Reds",
    "name": "James Allen (minors)",
    "pos": "RHP",
    "war": "",
    "g_as_pitcher": "",
    "ab": "",
    "hr": "",
    "ba": "",
    "ops": "",
    "g_as_batter": "",
    "w": "",
    "l": "",
    "era": "",
    "whip": "",
    "sv": "",
    "type": "4Yr",
    "drafted_out_of": "Kansas State University (Manhattan, KS)"
  },
  {
    "year": "2011",
    "round": "7",
    "draft_type": "",
    "overall_pick": "236",
    "round_pick": "25",
    "team": "Braves",
    "name": "Cody Martin (minors)",
    "pos": "RHP",
    "war": "",
    "g_as_pitcher": "",
    "ab": "",
    "hr": "",
    "ba": "",
    "ops": "",
    "g_as_batter": "",
    "w": "",
    "l": "",
    "era": "",
    "whip": "",
    "sv": "",
    "type": "4Yr",
    "drafted_out_of": "Gonzaga University (Spokane, WA)"
  },
  {
    "year": "2011",
    "round": "7",
    "draft_type": "",
    "overall_pick": "237",
    "round_pick": "26",
    "team": "Giants",
    "name": "Raymond Black (minors)",
    "pos": "RHP",
    "war": "",
    "g_as_pitcher": "",
    "ab": "",
    "hr": "",
    "ba": "",
    "ops": "",
    "g_as_batter": "",
    "w": "",
    "l": "",
    "era": "",
    "whip": "",
    "sv": "",
    "type": "4Yr",
    "drafted_out_of": "University of Pittsburgh (Pittsburgh, PA)"
  },
  {
    "year": "2011",
    "round": "7",
    "draft_type": "",
    "overall_pick": "238",
    "round_pick": "27",
    "team": "Twins",
    "name": "Steven Gruver (minors)",
    "pos": "LHP",
    "war": "",
    "g_as_pitcher": "",
    "ab": "",
    "hr": "",
    "ba": "",
    "ops": "",
    "g_as_batter": "",
    "w": "",
    "l": "",
    "era": "",
    "whip": "",
    "sv": "",
    "type": "4Yr",
    "drafted_out_of": "University of Tennessee (Knoxville, TN)"
  },
  {
    "year": "2011",
    "round": "7",
    "draft_type": "",
    "overall_pick": "239",
    "round_pick": "28",
    "team": "Yankees",
    "name": "Austin Jones (minors)",
    "pos": "1B",
    "war": "",
    "g_as_pitcher": "",
    "ab": "",
    "hr": "",
    "ba": "",
    "ops": "",
    "g_as_batter": "",
    "w": "",
    "l": "",
    "era": "",
    "whip": "",
    "sv": "",
    "type": "HS",
    "drafted_out_of": "Edmonds-Woodway HS (Edmonds, WA)"
  },
  {
    "year": "2011",
    "round": "7",
    "draft_type": "",
    "overall_pick": "240",
    "round_pick": "29",
    "team": "Rays",
    "name": "Ryan Carpenter (minors)",
    "pos": "LHP",
    "war": "",
    "g_as_pitcher": "",
    "ab": "",
    "hr": "",
    "ba": "",
    "ops": "",
    "g_as_batter": "",
    "w": "",
    "l": "",
    "era": "",
    "whip": "",
    "sv": "",
    "type": "4Yr",
    "drafted_out_of": "Gonzaga University (Spokane, WA)"
  },
  {
    "year": "2011",
    "round": "7",
    "draft_type": "",
    "overall_pick": "241",
    "round_pick": "30",
    "team": "Phillies",
    "name": "Ken Giles (minors)",
    "pos": "RHP",
    "war": "2.0",
    "g_as_pitcher": "44",
    "ab": "0",
    "hr": "0",
    "ba": "",
    "ops": "",
    "g_as_batter": "44",
    "w": "3",
    "l": "1",
    "era": "1.18",
    "whip": "0.79",
    "sv": "1",
    "type": "JC",
    "drafted_out_of": "Yavapai College (Prescott, AZ)"
  }
]
