[
  {
    "year": "2013",
    "round": "4",
    "draft_type": "",
    "overall_pick": "107",
    "round_pick": "1",
    "team": "Astros",
    "name": "Conrad Gregor (minors)",
    "pos": "1B",
    "war": "",
    "g_as_pitcher": "",
    "ab": "",
    "hr": "",
    "ba": "",
    "ops": "",
    "g_as_batter": "",
    "w": "",
    "l": "",
    "era": "",
    "whip": "",
    "sv": "",
    "type": "4Yr",
    "drafted_out_of": "Vanderbilt University (Nashville, TN)"
  },
  {
    "year": "2013",
    "round": "4",
    "draft_type": "",
    "overall_pick": "108",
    "round_pick": "2",
    "team": "Cubs",
    "name": "Tyler Skulina (minors)",
    "pos": "RHP",
    "war": "",
    "g_as_pitcher": "",
    "ab": "",
    "hr": "",
    "ba": "",
    "ops": "",
    "g_as_batter": "",
    "w": "",
    "l": "",
    "era": "",
    "whip": "",
    "sv": "",
    "type": "4Yr",
    "drafted_out_of": "Kent State University (Kent, OH)"
  },
  {
    "year": "2013",
    "round": "4",
    "draft_type": "",
    "overall_pick": "109",
    "round_pick": "3",
    "team": "Rockies",
    "name": "Jordan Patterson (minors)",
    "pos": "RF",
    "war": "",
    "g_as_pitcher": "",
    "ab": "",
    "hr": "",
    "ba": "",
    "ops": "",
    "g_as_batter": "",
    "w": "",
    "l": "",
    "era": "",
    "whip": "",
    "sv": "",
    "type": "4Yr",
    "drafted_out_of": "University of South Alabama (Mobile, AL)"
  },
  {
    "year": "2013",
    "round": "4",
    "draft_type": "",
    "overall_pick": "110",
    "round_pick": "4",
    "team": "Twins",
    "name": "Stephen Gonsalves (minors)",
    "pos": "LHP",
    "war": "",
    "g_as_pitcher": "",
    "ab": "",
    "hr": "",
    "ba": "",
    "ops": "",
    "g_as_batter": "",
    "w": "",
    "l": "",
    "era": "",
    "whip": "",
    "sv": "",
    "type": "HS",
    "drafted_out_of": "Cathedral Catholic HS (San Diego, CA)"
  },
  {
    "year": "2013",
    "round": "4",
    "draft_type": "",
    "overall_pick": "111",
    "round_pick": "5",
    "team": "Indians",
    "name": "Kyle Crockett (minors)",
    "pos": "LHP",
    "war": "1.1",
    "g_as_pitcher": "44",
    "ab": "0",
    "hr": "0",
    "ba": "",
    "ops": "",
    "g_as_batter": "43",
    "w": "4",
    "l": "1",
    "era": "1.80",
    "whip": "1.13",
    "sv": "0",
    "type": "4Yr",
    "drafted_out_of": "University of Virginia (Charlottesville, VA)"
  },
  {
    "year": "2013",
    "round": "4",
    "draft_type": "",
    "overall_pick": "112",
    "round_pick": "6",
    "team": "Marlins",
    "name": "K.J. Woods (minors)",
    "pos": "RF",
    "war": "",
    "g_as_pitcher": "",
    "ab": "",
    "hr": "",
    "ba": "",
    "ops": "",
    "g_as_batter": "",
    "w": "",
    "l": "",
    "era": "",
    "whip": "",
    "sv": "",
    "type": "HS",
    "drafted_out_of": "Fort Mill HS (Fort Mill, SC)"
  },
  {
    "year": "2013",
    "round": "4",
    "draft_type": "",
    "overall_pick": "113",
    "round_pick": "7",
    "team": "Red Sox",
    "name": "Myles Smith (minors)",
    "pos": "RHP",
    "war": "",
    "g_as_pitcher": "",
    "ab": "",
    "hr": "",
    "ba": "",
    "ops": "",
    "g_as_batter": "",
    "w": "",
    "l": "",
    "era": "",
    "whip": "",
    "sv": "",
    "type": "4Yr",
    "drafted_out_of": "Lee University (Cleveland, TN)"
  },
  {
    "year": "2013",
    "round": "4",
    "draft_type": "",
    "overall_pick": "114",
    "round_pick": "8",
    "team": "Royals",
    "name": "Zane Evans (minors)",
    "pos": "C",
    "war": "",
    "g_as_pitcher": "",
    "ab": "",
    "hr": "",
    "ba": "",
    "ops": "",
    "g_as_batter": "",
    "w": "",
    "l": "",
    "era": "",
    "whip": "",
    "sv": "",
    "type": "4Yr",
    "drafted_out_of": "Georgia Institute of Technology (Atlanta, GA)"
  },
  {
    "year": "2013",
    "round": "4",
    "draft_type": "",
    "overall_pick": "115",
    "round_pick": "9",
    "team": "Blue Jays",
    "name": "Evan Smith (minors)",
    "pos": "LHP",
    "war": "",
    "g_as_pitcher": "",
    "ab": "",
    "hr": "",
    "ba": "",
    "ops": "",
    "g_as_batter": "",
    "w": "",
    "l": "",
    "era": "",
    "whip": "",
    "sv": "",
    "type": "HS",
    "drafted_out_of": "Mary Montgomery HS (Semmes, AL)"
  },
  {
    "year": "2013",
    "round": "4",
    "draft_type": "",
    "overall_pick": "116",
    "round_pick": "10",
    "team": "Mets",
    "name": "L.J. Mazzilli (minors)",
    "pos": "2B",
    "war": "",
    "g_as_pitcher": "",
    "ab": "",
    "hr": "",
    "ba": "",
    "ops": "",
    "g_as_batter": "",
    "w": "",
    "l": "",
    "era": "",
    "whip": "",
    "sv": "",
    "type": "4Yr",
    "drafted_out_of": "University of Connecticut (Storrs, CT)"
  },
  {
    "year": "2013",
    "round": "4",
    "draft_type": "",
    "overall_pick": "117",
    "round_pick": "11",
    "team": "Mariners",
    "name": "Ryan Horstman (minors)",
    "pos": "LHP",
    "war": "",
    "g_as_pitcher": "",
    "ab": "",
    "hr": "",
    "ba": "",
    "ops": "",
    "g_as_batter": "",
    "w": "",
    "l": "",
    "era": "",
    "whip": "",
    "sv": "",
    "type": "4Yr",
    "drafted_out_of": "St. John's University (Queens, NY)"
  },
  {
    "year": "2013",
    "round": "4",
    "draft_type": "",
    "overall_pick": "118",
    "round_pick": "12",
    "team": "Padres",
    "name": "Mason Smith (minors)",
    "pos": "CF",
    "war": "",
    "g_as_pitcher": "",
    "ab": "",
    "hr": "",
    "ba": "",
    "ops": "",
    "g_as_batter": "",
    "w": "",
    "l": "",
    "era": "",
    "whip": "",
    "sv": "",
    "type": "HS",
    "drafted_out_of": "Rocky Mountain HS (Meridian, ID)"
  },
  {
    "year": "2013",
    "round": "4",
    "draft_type": "",
    "overall_pick": "119",
    "round_pick": "13",
    "team": "Pirates",
    "name": "Cody Dickson (minors)",
    "pos": "LHP",
    "war": "",
    "g_as_pitcher": "",
    "ab": "",
    "hr": "",
    "ba": "",
    "ops": "",
    "g_as_batter": "",
    "w": "",
    "l": "",
    "era": "",
    "whip": "",
    "sv": "",
    "type": "4Yr",
    "drafted_out_of": "Sam Houston State University (Huntsville, TX)"
  },
  {
    "year": "2013",
    "round": "4",
    "draft_type": "",
    "overall_pick": "120",
    "round_pick": "14",
    "team": "Diamondbacks",
    "name": "Matt McPhearson (minors)",
    "pos": "CF",
    "war": "",
    "g_as_pitcher": "",
    "ab": "",
    "hr": "",
    "ba": "",
    "ops": "",
    "g_as_batter": "",
    "w": "",
    "l": "",
    "era": "",
    "whip": "",
    "sv": "",
    "type": "HS",
    "drafted_out_of": "Riverdale Baptist HS (Upper Marlboro, MD)"
  },
  {
    "year": "2013",
    "round": "4",
    "draft_type": "",
    "overall_pick": "121",
    "round_pick": "15",
    "team": "Phillies",
    "name": "Jake Sweaney (minors)",
    "pos": "C",
    "war": "",
    "g_as_pitcher": "",
    "ab": "",
    "hr": "",
    "ba": "",
    "ops": "",
    "g_as_batter": "",
    "w": "",
    "l": "",
    "era": "",
    "whip": "",
    "sv": "",
    "type": "HS",
    "drafted_out_of": "Garces Memorial HS (Bakersfield, CA)"
  },
  {
    "year": "2013",
    "round": "4",
    "draft_type": "",
    "overall_pick": "122",
    "round_pick": "16",
    "team": "Brewers",
    "name": "Taylor Williams (minors)",
    "pos": "RHP",
    "war": "",
    "g_as_pitcher": "",
    "ab": "",
    "hr": "",
    "ba": "",
    "ops": "",
    "g_as_batter": "",
    "w": "",
    "l": "",
    "era": "",
    "whip": "",
    "sv": "",
    "type": "4Yr",
    "drafted_out_of": "Kent State University (Kent, OH)"
  },
  {
    "year": "2013",
    "round": "4",
    "draft_type": "",
    "overall_pick": "123",
    "round_pick": "17",
    "team": "White Sox",
    "name": "Andrew Mitchell (minors)",
    "pos": "RHP",
    "war": "",
    "g_as_pitcher": "",
    "ab": "",
    "hr": "",
    "ba": "",
    "ops": "",
    "g_as_batter": "",
    "w": "",
    "l": "",
    "era": "",
    "whip": "",
    "sv": "",
    "type": "4Yr",
    "drafted_out_of": "Texas Christian University (Fort Worth, TX)"
  },
  {
    "year": "2013",
    "round": "4",
    "draft_type": "",
    "overall_pick": "124",
    "round_pick": "18",
    "team": "Dodgers",
    "name": "Cody Bellinger (minors)",
    "pos": "1B",
    "war": "",
    "g_as_pitcher": "",
    "ab": "",
    "hr": "",
    "ba": "",
    "ops": "",
    "g_as_batter": "",
    "w": "",
    "l": "",
    "era": "",
    "whip": "",
    "sv": "",
    "type": "HS",
    "drafted_out_of": "Hamilton HS (Chandler, AZ)"
  },
  {
    "year": "2013",
    "round": "4",
    "draft_type": "",
    "overall_pick": "125",
    "round_pick": "19",
    "team": "Cardinals",
    "name": "Mason Katz (minors)",
    "pos": "2B",
    "war": "",
    "g_as_pitcher": "",
    "ab": "",
    "hr": "",
    "ba": "",
    "ops": "",
    "g_as_batter": "",
    "w": "",
    "l": "",
    "era": "",
    "whip": "",
    "sv": "",
    "type": "4Yr",
    "drafted_out_of": "Louisiana State University (Baton Rouge, LA)"
  },
  {
    "year": "2013",
    "round": "4",
    "draft_type": "",
    "overall_pick": "126",
    "round_pick": "20",
    "team": "Tigers",
    "name": "Austin Kubitza (minors)",
    "pos": "RHP",
    "war": "",
    "g_as_pitcher": "",
    "ab": "",
    "hr": "",
    "ba": "",
    "ops": "",
    "g_as_batter": "",
    "w": "",
    "l": "",
    "era": "",
    "whip": "",
    "sv": "",
    "type": "4Yr",
    "drafted_out_of": "Rice University (Houston, TX)"
  },
  {
    "year": "2013",
    "round": "4",
    "draft_type": "",
    "overall_pick": "127",
    "round_pick": "21",
    "team": "Angels",
    "name": "Elliot Morris (minors)",
    "pos": "RHP",
    "war": "",
    "g_as_pitcher": "",
    "ab": "",
    "hr": "",
    "ba": "",
    "ops": "",
    "g_as_batter": "",
    "w": "",
    "l": "",
    "era": "",
    "whip": "",
    "sv": "",
    "type": "JC",
    "drafted_out_of": "Pierce College (Lakewood, WA)"
  },
  {
    "year": "2013",
    "round": "4",
    "draft_type": "",
    "overall_pick": "128",
    "round_pick": "22",
    "team": "Rays",
    "name": "Kean Wong (minors)",
    "pos": "2B",
    "war": "",
    "g_as_pitcher": "",
    "ab": "",
    "hr": "",
    "ba": "",
    "ops": "",
    "g_as_batter": "",
    "w": "",
    "l": "",
    "era": "",
    "whip": "",
    "sv": "",
    "type": "HS",
    "drafted_out_of": "Waiakea HS (Waiakea, HI)"
  },
  {
    "year": "2013",
    "round": "4",
    "draft_type": "",
    "overall_pick": "129",
    "round_pick": "23",
    "team": "Orioles",
    "name": "Jonah Heim (minors)",
    "pos": "C",
    "war": "",
    "g_as_pitcher": "",
    "ab": "",
    "hr": "",
    "ba": "",
    "ops": "",
    "g_as_batter": "",
    "w": "",
    "l": "",
    "era": "",
    "whip": "",
    "sv": "",
    "type": "HS",
    "drafted_out_of": "Amherst HS (Snyder, NY)"
  },
  {
    "year": "2013",
    "round": "4",
    "draft_type": "",
    "overall_pick": "130",
    "round_pick": "24",
    "team": "Rangers",
    "name": "Isaiah Kiner-Falefa (minors)",
    "pos": "SS",
    "war": "",
    "g_as_pitcher": "",
    "ab": "",
    "hr": "",
    "ba": "",
    "ops": "",
    "g_as_batter": "",
    "w": "",
    "l": "",
    "era": "",
    "whip": "",
    "sv": "",
    "type": "HS",
    "drafted_out_of": "Mid Pacific Institute HS (Honolulu, HI)"
  },
  {
    "year": "2013",
    "round": "4",
    "draft_type": "",
    "overall_pick": "131",
    "round_pick": "25",
    "team": "Athletics",
    "name": "Dylan Covey (minors)",
    "pos": "RHP",
    "war": "",
    "g_as_pitcher": "",
    "ab": "",
    "hr": "",
    "ba": "",
    "ops": "",
    "g_as_batter": "",
    "w": "",
    "l": "",
    "era": "",
    "whip": "",
    "sv": "",
    "type": "4Yr",
    "drafted_out_of": "University of San Diego (San Diego, CA)"
  },
  {
    "year": "2013",
    "round": "4",
    "draft_type": "",
    "overall_pick": "132",
    "round_pick": "26",
    "team": "Giants",
    "name": "Brian Ragira (minors)",
    "pos": "1B",
    "war": "",
    "g_as_pitcher": "",
    "ab": "",
    "hr": "",
    "ba": "",
    "ops": "",
    "g_as_batter": "",
    "w": "",
    "l": "",
    "era": "",
    "whip": "",
    "sv": "",
    "type": "4Yr",
    "drafted_out_of": "Stanford University (Palo Alto, CA)"
  },
  {
    "year": "2013",
    "round": "4",
    "draft_type": "",
    "overall_pick": "133",
    "round_pick": "27",
    "team": "Braves",
    "name": "Tanner Murphy (minors)",
    "pos": "C",
    "war": "",
    "g_as_pitcher": "",
    "ab": "",
    "hr": "",
    "ba": "",
    "ops": "",
    "g_as_batter": "",
    "w": "",
    "l": "",
    "era": "",
    "whip": "",
    "sv": "",
    "type": "HS",
    "drafted_out_of": "Malden HS (Malden, MO)"
  },
  {
    "year": "2013",
    "round": "4",
    "draft_type": "",
    "overall_pick": "134",
    "round_pick": "28",
    "team": "Yankees",
    "name": "Tyler Wade (minors)",
    "pos": "SS",
    "war": "",
    "g_as_pitcher": "",
    "ab": "",
    "hr": "",
    "ba": "",
    "ops": "",
    "g_as_batter": "",
    "w": "",
    "l": "",
    "era": "",
    "whip": "",
    "sv": "",
    "type": "HS",
    "drafted_out_of": "Murrieta Valley HS (Murrieta, CA)"
  },
  {
    "year": "2013",
    "round": "4",
    "draft_type": "",
    "overall_pick": "135",
    "round_pick": "29",
    "team": "Reds",
    "name": "Ben Lively (minors)",
    "pos": "RHP",
    "war": "",
    "g_as_pitcher": "",
    "ab": "",
    "hr": "",
    "ba": "",
    "ops": "",
    "g_as_batter": "",
    "w": "",
    "l": "",
    "era": "",
    "whip": "",
    "sv": "",
    "type": "4Yr",
    "drafted_out_of": "University of Central Florida (Orlando, FL)"
  },
  {
    "year": "2013",
    "round": "4",
    "draft_type": "",
    "overall_pick": "136",
    "round_pick": "30",
    "team": "Nationals",
    "name": "Nick Pivetta (minors)",
    "pos": "RHP",
    "war": "",
    "g_as_pitcher": "",
    "ab": "",
    "hr": "",
    "ba": "",
    "ops": "",
    "g_as_batter": "",
    "w": "",
    "l": "",
    "era": "",
    "whip": "",
    "sv": "",
    "type": "JC",
    "drafted_out_of": "New Mexico Junior College (Hobbs, NM)"
  }
]
